Dtautils/__init__.py
Dtautils/data_factory.py
Dtautils/settings.py
Dtautils/tools.py
Dtautils/web_crawler.py
Dtautils-0.8.16.dist-info/LICENSE
Dtautils-0.8.16.dist-info/METADATA
Dtautils-0.8.16.dist-info/WHEEL
Dtautils-0.8.16.dist-info/top_level.txt
Dtautils-0.8.16.dist-info/RECORD
