Metadata-Version: 2.1
Name: Dtautils
Version: 0.8.16
Summary: some utils to process data easy
Home-page: https://github.com/gitduk/utils
Author: kaige
Author-email: wdkany@gmail.com
License: MIT
Platform: UNKNOWN
Classifier: License :: OSI Approved :: MIT License
Classifier: Programming Language :: Python
Classifier: Programming Language :: Python :: 3
Classifier: Programming Language :: Python :: 3.6
Classifier: Programming Language :: Python :: Implementation :: CPython
Classifier: Programming Language :: Python :: Implementation :: PyPy
Requires-Python: >=3.6.0
Requires-Dist: logging
Requires-Dist: parsel
Requires-Dist: pymysql
Requires-Dist: requests
